{
"type": "FeatureCollection",
"name": "003_ida_stops",
"crs": { "type": "name", "properties": { "name": "urn:ogc:def:crs:OGC:1.3:CRS84" } },
"features": [
{ "type": "Feature", "properties": { "id": "14010755", "routeId": "14010754", "sequence": 0, "travelTime": 147930995, "dwellTime": 31, "arrivalTim": 0, "departureT": 8, "passengerA": 147930995, "passengerB": 147930998 }, "geometry": { "type": "Point", "coordinates": [ -96.927155038885431, 19.542439663074624 ] } },
{ "type": "Feature", "properties": { "id": "14010757", "routeId": "14010754", "sequence": 1, "travelTime": 556, "dwellTime": 18, "arrivalTim": 0, "departureT": 7, "passengerA": 147931053, "passengerB": 147931055 }, "geometry": { "type": "Point", "coordinates": [ -96.920438102053694, 19.536533454101573 ] } },
{ "type": "Feature", "properties": { "id": "14010759", "routeId": "14010754", "sequence": 2, "travelTime": 101, "dwellTime": 13, "arrivalTim": 5, "departureT": 1, "passengerA": 147931065, "passengerB": 147931067 }, "geometry": { "type": "Point", "coordinates": [ -96.917202481385161, 19.53537569782436 ] } },
{ "type": "Feature", "properties": { "id": "14010761", "routeId": "14010754", "sequence": 3, "travelTime": 158, "dwellTime": 9, "arrivalTim": 1, "departureT": 3, "passengerA": 147931082, "passengerB": 147931083 }, "geometry": { "type": "Point", "coordinates": [ -96.914284374894407, 19.531620948049873 ] } },
{ "type": "Feature", "properties": { "id": "14010763", "routeId": "14010754", "sequence": 4, "travelTime": 137, "dwellTime": 8, "arrivalTim": 1, "departureT": 0, "passengerA": 147931097, "passengerB": 147931098 }, "geometry": { "type": "Point", "coordinates": [ -96.910867317552885, 19.527481359943859 ] } },
{ "type": "Feature", "properties": { "id": "14010765", "routeId": "14010754", "sequence": 5, "travelTime": 82, "dwellTime": 2, "arrivalTim": 1, "departureT": 0, "passengerA": 147931106, "passengerB": 147931106 }, "geometry": { "type": "Point", "coordinates": [ -96.908697637338236, 19.525992222272503 ] } },
{ "type": "Feature", "properties": { "id": "14010767", "routeId": "14010754", "sequence": 6, "travelTime": 141, "dwellTime": 16, "arrivalTim": 1, "departureT": 2, "passengerA": 147931120, "passengerB": 147931122 }, "geometry": { "type": "Point", "coordinates": [ -96.90709494672673, 19.52555759098653 ] } },
{ "type": "Feature", "properties": { "id": "14010769", "routeId": "14010754", "sequence": 7, "travelTime": 271, "dwellTime": 2, "arrivalTim": 3, "departureT": 0, "passengerA": 147931149, "passengerB": 147931149 }, "geometry": { "type": "Point", "coordinates": [ -96.885647620005727, 19.520341924364391 ] } },
{ "type": "Feature", "properties": { "id": "14010771", "routeId": "14010754", "sequence": 8, "travelTime": 38, "dwellTime": 9, "arrivalTim": 3, "departureT": 0, "passengerA": 147931153, "passengerB": 147931154 }, "geometry": { "type": "Point", "coordinates": [ -96.885458623471351, 19.520320548335143 ] } }
]
}
